infinitystones/__init__.py
infinitystones/config.py
infinitystones/utils.py
infinitystones/timestone/__init__.py
infinitystones/timestone/client/__init__.py
infinitystones/timestone/client/api_client.py
infinitystones/timestone/client/exceptions.py
infinitystones/timestone/config/__init__.py
infinitystones/timestone/config/settings.py
infinitystones/timestone/utils/__init__.py
infinitystones/timestone/utils/time_utils.py
infinitystones-0.1.3.dist-info/METADATA
infinitystones-0.1.3.dist-info/WHEEL
infinitystones-0.1.3.dist-info/licenses/LICENSE
infinitystones-0.1.3.dist-info/RECORD
